{
  "rabbit_version": "3.7.15",
  "users": [
    {
      "name": "service",
      "password_hash": "c0s5Miga4KQv5aZFznp2IJUzxPrO0coJKGNXqhM72M/GSR8x",
      "hashing_algorithm": "rabbit_password_hashing_sha256",
      "tags": ""
    },
    {
      "name": "admin",
      "password_hash": "yWbKjfnPO7yHKzA6V2ohPkdDsGnCM15GHyqUuJQu4Kx6+EDP",
      "hashing_algorithm": "rabbit_password_hashing_sha256",
      "tags": "administrator"
    }
  ],
  "vhosts": [
    {
      "name": "/"
    }
  ],
  "permissions": [
    {
      "user": "service",
      "vhost": "/",
      "configure": ".*",
      "write": ".*",
      "read": ".*"
    },
    {
      "user": "admin",
      "vhost": "/",
      "configure": ".*",
      "write": ".*",
      "read": ".*"
    }
  ],
  "topic_permissions": [
    {
      "user": "service",
      "vhost": "/",
      "exchange": "",
      "write": ".*",
      "read": ".*"
    }
  ],
  "parameters": [],
  "global_parameters": [
    {
      "name": "cluster_name",
      "value": "rabbit@rabbit"
    }
  ],
  "policies": [],
  "queues": [],
  "exchanges": [],
  "bindings": []
}